regmonkey/__init__.py
regmonkey/stats.py
regmonkey-0.1.4.dist-info/licenses/LICENSE
regmonkey-0.1.4.dist-info/METADATA
regmonkey-0.1.4.dist-info/WHEEL
regmonkey-0.1.4.dist-info/top_level.txt
regmonkey-0.1.4.dist-info/RECORD
