Metadata-Version: 2.4
Name: regmonkey
Version: 0.1.4
Summary: A smart and lightweight toolkit for regression modeling, statistical summaries, and Excel annotations.
Author-email: qingrui <qingrui.econ@gmail.com>
License: MIT
Keywords: regression,statistics,excel,data-analysis,summary,dummy-variable
Classifier: Programming Language :: Python :: 3
Classifier: License :: OSI Approved :: MIT License
Classifier: Intended Audience :: Science/Research
Classifier: Topic :: Scientific/Engineering :: Information Analysis
Requires-Python: >=3.7
License-File: LICENSE
Requires-Dist: pandas>=1.0
Requires-Dist: numpy>=1.18
Requires-Dist: openpyxl>=3.0
Requires-Dist: statsmodels>=0.13
Dynamic: license-file
